abcreate/__init__.py
abcreate/_version.py
abcreate/bundle/Info.plist
abcreate/bundle/__init__.py
abcreate/bundle/bundle.py
abcreate/bundle/executable.py
abcreate/bundle/executables.py
abcreate/bundle/framework.py
abcreate/bundle/frameworks.py
abcreate/bundle/icon.py
abcreate/bundle/icons.py
abcreate/bundle/libraries.py
abcreate/bundle/library.py
abcreate/bundle/locale.py
abcreate/bundle/locales.py
abcreate/bundle/plist.py
abcreate/bundle/resource.py
abcreate/bundle/resources.py
abcreate/bundle/symlink.py
abcreate/bundle/gtk/__init__.py
abcreate/bundle/gtk/gdkpixbuf.py
abcreate/bundle/gtk/gir.py
abcreate/bundle/gtk/glib.py
abcreate/bundle/gtk/gtk3.py
abcreate/bundle/gtk/gtk4.py
abcreate/util/__init__.py
abcreate/util/linkedobject.py
abcreate/util/log.py
abcreate/util/path.py
abcreate-0.6.dist-info/METADATA
abcreate-0.6.dist-info/WHEEL
abcreate-0.6.dist-info/entry_points.txt
abcreate-0.6.dist-info/licenses/LICENSE
abcreate-0.6.dist-info/RECORD
