Metadata-Version: 2.4
Name: abcreate
Version: 0.6
Summary: application bundle creator
Project-URL: Bug Reports, https://github.com/dehesselle/abcreate/issues
Project-URL: Source, https://github.com/dehesselle/abcreate
Author-email: René de Hesselle <dehesselle@web.de>
License:                     GNU GENERAL PUBLIC LICENSE
License-File: LICENSE
Classifier: Development Status :: 3 - Alpha
Classifier: Environment :: Console
Classifier: Environment :: MacOS X
Classifier: Intended Audience :: Developers
Classifier: License :: OSI Approved :: GNU General Public License v2 or later (GPLv2+)
Classifier: Operating System :: MacOS :: MacOS X
Classifier: Programming Language :: Python :: 3
Classifier: Programming Language :: Python :: 3 :: Only
Classifier: Programming Language :: Python :: 3.10
Classifier: Topic :: Software Development :: Build Tools
Classifier: Topic :: Utilities
Requires-Python: >=3.10
Requires-Dist: lxml>=5.3.1
Requires-Dist: pydantic-xml>=2.14.1
